MANIFEST.in
README
setup.py
django_farm.egg-info/PKG-INFO
django_farm.egg-info/SOURCES.txt
django_farm.egg-info/dependency_links.txt
django_farm.egg-info/top_level.txt
django_farm.egg-info/zip-safe
farm/__init__.py
farm/admin.py
farm/managers.py
farm/models.py
farm/tests.py
farm/urls.py
farm/utils.py
farm/views.py
farm/templates/_animals_list.html
farm/templates/farm/animal_list.html
farm/templates/farm/base.html
farm/templatetags/__init__.py
farm/templatetags/farm_tags.py